MANIFEST.in
RELEASE-VERSION
setup.py
svnversion.py
ilogue/__init__.py
ilogue/readable/AssertableContext.py
ilogue/readable/AssertableDocument.py
ilogue/readable/AssertableFileDownload.py
ilogue/readable/AssertableFileResponse.py
ilogue/readable/AssertableRequest.py
ilogue/readable/ContextProviderMock.py
ilogue/readable/FormInteraction.py
ilogue/readable/FormMatcher.py
ilogue/readable/FragmentMatcher.py
ilogue/readable/GeneralMatcher.py
ilogue/readable/LinkMatcher.py
ilogue/readable/MockImplementation.py
ilogue/readable/PageList.py
ilogue/readable/PageSection.py
ilogue/readable/__init__.py
ilogue/readable/alchemymatcher.py
ilogue/readable/assertableassertion.py
ilogue/readable/assertablemethod.py
ilogue/readable/assertableobject.py
ilogue/readable/assertableresponse.py
ilogue/readable/callmatch.py
ilogue/readable/configurablemethod.py
ilogue/readable/datetimematcher.py
ilogue/readable/formmatcher.py
ilogue/readable/matcher.py
ilogue/readable/matching.py
ilogue/readable/null.py
ilogue/readable/stringmatcher.py
ilogue/readable/xmlelementbuilder.py
ilogue/readable/xmlmatcher.py
ilogue/readable/tests/__init__.py
ilogue/readable/tests/fast/__init__.py
ilogue/readable/tests/fast/test_AssertableDocument.py
ilogue/readable/tests/fast/test_FormInteraction.py
ilogue/readable/tests/fast/test_FormMatcher.py
ilogue/readable/tests/fast/test_FragmentMatcher.py
ilogue/readable/tests/fast/test_MockImplementation.py
ilogue/readable/tests/fast/test_PageList.py
ilogue/readable/tests/fast/test_assertableFileDownload.py
ilogue/readable/tests/fast/test_assertablecontext.py
ilogue/readable/tests/fast/test_assertablecontrol.py
ilogue/readable/tests/fast/test_assertablemethod.py
ilogue/readable/tests/fast/test_assertableobject.py
ilogue/readable/tests/fast/test_assertableresponse.py
ilogue/readable/tests/fast/test_configurablemethod.py
ilogue/readable/tests/fast/test_datetimeMatcher.py
ilogue/readable/tests/fast/test_formmatcher.py
ilogue/readable/tests/slow/__init__.py
readable.egg-info/PKG-INFO
readable.egg-info/SOURCES.txt
readable.egg-info/dependency_links.txt
readable.egg-info/namespace_packages.txt
readable.egg-info/not-zip-safe
readable.egg-info/requires.txt
readable.egg-info/top_level.txt