Metadata-Version: 1.1
Name: readable
Version: 0.0.post30
Summary: testing and assertion library
Home-page: http://ilogue.com
Author: Jasper van den Bosch
Author-email: jasper@ilogue.com
License: UNKNOWN
Platform: UNKNOWN
Classifier: Programming Language :: Python
Classifier: License :: Other/Proprietary License
Classifier: Development Status :: 1 - Planning
Classifier: Intended Audience :: Developers
Classifier: Topic :: Software Development :: Testing
